mailers/__init__.py
mailers/encrypters/__init__.py
mailers/encrypters/base.py
mailers/exceptions.py
mailers/factories.py
mailers/mailer.py
mailers/message.py
mailers/preprocessors/__init__.py
mailers/preprocessors/cssliner.py
mailers/preprocessors/remove_html_comments.py
mailers/py.typed
mailers/pytest_plugin.py
mailers/signers/__init__.py
mailers/signers/base.py
mailers/signers/dkim.py
mailers/transports/__init__.py
mailers/transports/base.py
mailers/transports/console.py
mailers/transports/file.py
mailers/transports/memory.py
mailers/transports/multi.py
mailers/transports/null.py
mailers/transports/smtp.py
mailers/transports/stream.py
mailers-3.2.0.dist-info/LICENSE
mailers-3.2.0.dist-info/METADATA
mailers-3.2.0.dist-info/WHEEL
mailers-3.2.0.dist-info/entry_points.txt
mailers-3.2.0.dist-info/RECORD
