Metadata-Version: 2.1
Name: mailers
Version: 3.2.0
Summary: Email delivery for asyncio.
Home-page: https://github.com/alex-oleshkevich/mailers
License: MIT
Keywords: asyncio,email,mailer,mail
Author: alex.oleshkevich
Author-email: alex.oleshkevich@gmail.com
Requires-Python: >=3.8,<4.0
Classifier: Development Status :: 5 - Production/Stable
Classifier: Environment :: Web Environment
Classifier: Intended Audience :: Developers
Classifier: License :: OSI Approved :: MIT License
Classifier: Operating System :: OS Independent
Classifier: Programming Language :: Python :: 3
Classifier: Programming Language :: Python :: 3.8
Classifier: Programming Language :: Python :: 3.9
Classifier: Programming Language :: Python :: 3.10
Classifier: Programming Language :: Python :: 3.11
Classifier: Programming Language :: Python :: 3.12
Classifier: Programming Language :: Python :: 3.13
Classifier: Topic :: Software Development :: Libraries :: Python Modules
Classifier: Typing :: Typed
Provides-Extra: css-inline
Provides-Extra: dkim
Provides-Extra: jinja2
Provides-Extra: smtp
Requires-Dist: aiosmtplib (>=3.0,<4.0) ; extra == "smtp"
Requires-Dist: anyio (>=3.7.1,<5)
Requires-Dist: css_inline (>=0.14) ; extra == "css-inline"
Requires-Dist: dkimpy (>=1.0,<2.0) ; extra == "dkim"
Requires-Dist: jinja2 (>=3.0,<4.0) ; extra == "jinja2"
Project-URL: Documentation, https://github.com/alex-oleshkevich/mailers
Project-URL: Repository, https://github.com/alex-oleshkevich/mailers.git
